smash/__init__.py
smash/__main__.py
smash/cli.py
smash/config.py
smash/smash.py
smash/status.py
smash/version.py
smash/xbar.py
smash_clients-0.4.2.dist-info/METADATA
smash_clients-0.4.2.dist-info/WHEEL
smash_clients-0.4.2.dist-info/entry_points.txt
smash_clients-0.4.2.dist-info/top_level.txt
smash_clients-0.4.2.dist-info/RECORD
