Metadata-Version: 2.1
Name: smash-clients
Version: 0.4.2
Summary: Smash clients
Home-page: https://p0nk.net/software/smash
Author: dlek
Author-email: dlek@p0nk.net
License: MIT license
Requires-Python: >=3.6
Requires-Dist: requests
Requires-Dist: emoji
Requires-Dist: mergeconf ==0.5.2
